cbc/__init__.py
cbc/content.py
cbc/pipeline.py
cbc/data/__init__.py
cbc/data/bw_rs_feed.xml
cbc/data/dewiki_simple_short.txt
cbc/data/rki_rs_feed.xml
cbc/nlp/__init__.py
cbc/nlp/base.py
cbc/nlp/pdftools.py
cbc/nlp/rss_scraping.py
cbc/nlp/translate.py
cbc/nlp/w2v_const.py
cbc/nlp/w2v_test_cases.py
cbc/nlp/w2v_test_framework.py
cbc/nlp/wikitools.py
cbc/nlp/word2vec_tools.py
cbc_nlp-0.0.1.dist-info/LICENSE
cbc_nlp-0.0.1.dist-info/METADATA
cbc_nlp-0.0.1.dist-info/WHEEL
cbc_nlp-0.0.1.dist-info/top_level.txt
cbc_nlp-0.0.1.dist-info/RECORD
