Metadata-Version: 2.1
Name: cbc-nlp
Version: 0.0.1
Summary: Simplify NLP pre-processing.
Author-email: "Consileon.ai" <ai@consileon.de>
License: Apache License
Project-URL: Homepage, https://github.com/consileon-ai/cbc-nlp
Project-URL: ConsileonAI, https://consileon.ai/
Keywords: NLP,pipeline,AI
Classifier: Development Status :: 4 - Beta
Classifier: Programming Language :: Python
Classifier: Programming Language :: Python :: 3
License-File: LICENSE
Requires-Dist: numpy
Requires-Dist: spacy
Requires-Dist: nltk
Requires-Dist: gensim
Requires-Dist: tika
Requires-Dist: boto3
Requires-Dist: beautifulsoup4
Requires-Dist: lxml
Requires-Dist: s3-streaming
Provides-Extra: dev
Requires-Dist: pytest ; extra == 'dev'
Requires-Dist: pip-tools ; extra == 'dev'
